[{"author": {"state": "active", "avatar_url": "http://cdn.libravatar.org/avatar/79ebee40dd44c661fc4ad27b3656be68?s=40&d=identicon", "id": 252, "name": "\u00c1lvaro Fernando Matos de Souza", "username": "alvarofernandoms"}, "id": 10545, "body": "_Status changed to closed_", "created_at": "2016-03-23T18:46:56.290Z", "attachment": null}, {"author": {"state": "active", "avatar_url": "http://cdn.libravatar.org/avatar/79ebee40dd44c661fc4ad27b3656be68?s=40&d=identicon", "id": 252, "name": "\u00c1lvaro Fernando Matos de Souza", "username": "alvarofernandoms"}, "id": 10544, "body": "_Assignee removed_", "created_at": "2016-03-23T18:46:24.647Z", "attachment": null}]