[{"author": {"state": "active", "avatar_url": "http://cdn.libravatar.org/avatar/800e3af93350753db9dee1864cef10ff?s=40&d=identicon", "id": 5, "name": "Thiago Ribeiro", "username": "thiago"}, "id": 7187, "body": "se esse erro voltar a acontecer, por favor, reabram a issue.", "created_at": "2016-01-05T12:08:35.178Z", "attachment": null}, {"author": {"state": "active", "avatar_url": "http://cdn.libravatar.org/avatar/800e3af93350753db9dee1864cef10ff?s=40&d=identicon", "id": 5, "name": "Thiago Ribeiro", "username": "thiago"}, "id": 7186, "body": "_Status changed to closed_", "created_at": "2016-01-05T12:08:35.159Z", "attachment": null}, {"author": {"state": "active", "avatar_url": "http://cdn.libravatar.org/avatar/800e3af93350753db9dee1864cef10ff?s=40&d=identicon", "id": 5, "name": "Thiago Ribeiro", "username": "thiago"}, "id": 6718, "body": "atualizamos a vers\u00e3o do jquery do colab-spb para 2.1\r\nesperamos que com isso o bug suma\r\natualiza\u00e7\u00e3o provavel na quinta.", "created_at": "2015-12-16T19:52:24.444Z", "attachment": null}, {"author": {"state": "active", "avatar_url": "http://cdn.libravatar.org/avatar/c8b72d0556872a2aea21e8fed0a72001?s=40&d=identicon", "id": 129, "name": "Melissa Wen", "username": "melissawen"}, "id": 6524, "body": "@daniela est\u00e1 funcionando! valeu!", "created_at": "2015-12-14T13:05:48.072Z", "attachment": null}, {"author": {"state": "active", "avatar_url": "http://cdn.libravatar.org/avatar/0743c2eb05e68c92baa5f8c498995a20?s=40&d=identicon", "id": 300, "name": "Daniela Feitosa", "username": "daniela"}, "id": 6522, "body": "@melissawen, testa o \"Adicionar institui\u00e7\u00e3o\" no [openAcs](https://dev.softwarepublico.gov.br/social/profile/openacs/plugin/organization_ratings/new_rating). S\u00f3 para testar, desabilitei l\u00e1 o que estava causando o erro (#568).", "created_at": "2015-12-12T16:24:57.232Z", "attachment": null}, {"author": {"state": "active", "avatar_url": "http://cdn.libravatar.org/avatar/8929f5e2c6b39a0a8afb4630b116faab?s=40&d=identicon", "id": 79, "name": "Fabio Teixeira", "username": "fabio1079"}, "id": 6518, "body": "_mentioned in issue #568_", "created_at": "2015-12-11T21:15:03.405Z", "attachment": null}, {"author": {"state": "active", "avatar_url": "http://cdn.libravatar.org/avatar/8929f5e2c6b39a0a8afb4630b116faab?s=40&d=identicon", "id": 79, "name": "Fabio Teixeira", "username": "fabio1079"}, "id": 6479, "body": "O erro vem da fun\u00e7\u00e3o jQuery.fn.center, que n\u00e3o est\u00e1 presente na vers\u00e3o 2.0.3 que \u00e9 a ultima carregada(sobrescrevendo as demais). O noosfero por padr\u00e3o usa a vers\u00e3o 2.1.1, sugiro atualizar essa 2.0.3 para a 2.1.1.\r\n\r\nSe no console do navegador digitar: jQuery.fn.jquery \u00e9 poss\u00edvel ver qual a vers\u00e3o utilizada pelo site.\r\n  ", "created_at": "2015-12-11T14:06:17.081Z", "attachment": "jquery203.png"}, {"author": {"state": "active", "avatar_url": "http://cdn.libravatar.org/avatar/f1c4e7359f83d87a9b8ffc5a003e9cc9?s=40&d=identicon", "id": 17, "name": "Alexandre Barbosa", "username": "alexandre"}, "id": 6477, "body": "@simiaosimis @fabio1079 ", "created_at": "2015-12-11T13:45:22.345Z", "attachment": null}, {"author": {"state": "active", "avatar_url": "http://cdn.libravatar.org/avatar/c8b72d0556872a2aea21e8fed0a72001?s=40&d=identicon", "id": 129, "name": "Melissa Wen", "username": "melissawen"}, "id": 6396, "body": "@kanashiro @seocam ", "created_at": "2015-12-10T16:04:57.859Z", "attachment": null}, {"author": {"state": "active", "avatar_url": "http://cdn.libravatar.org/avatar/c8b72d0556872a2aea21e8fed0a72001?s=40&d=identicon", "id": 129, "name": "Melissa Wen", "username": "melissawen"}, "id": 6395, "body": "Na p\u00e1gina de edi\u00e7\u00e3o de blocos, ao clicar no bot\u00e3o de edi\u00e7\u00e3o de um bloco comum (menu est\u00e1tico) do noosfero, uma p\u00e1gina \u00e9 carregada sem formata\u00e7\u00e3o com os campos a serem formatados.\r\nDeveria carregar, na mesma p\u00e1gina de edi\u00e7\u00e3o, um lightbox com os campos a serem editados", "created_at": "2015-12-10T16:04:32.920Z", "attachment": "Captura_de_tela_de_2015-12-10_12-12-39.png"}, {"author": {"state": "active", "avatar_url": "http://cdn.libravatar.org/avatar/c8b72d0556872a2aea21e8fed0a72001?s=40&d=identicon", "id": 129, "name": "Melissa Wen", "username": "melissawen"}, "id": 6394, "body": "Adicionar institui\u00e7\u00e3o com dados incorretos (deveria gerar aviso de erro), mas a p\u00e1gina para de funcionar e congela com a transpar\u00eancia preta do lightbox... apenas retorna a p\u00e1gina dando refresh", "created_at": "2015-12-10T16:02:31.321Z", "attachment": "print_modal.jpg"}, {"author": {"state": "active", "avatar_url": "http://cdn.libravatar.org/avatar/c8b72d0556872a2aea21e8fed0a72001?s=40&d=identicon", "id": 129, "name": "Melissa Wen", "username": "melissawen"}, "id": 6393, "body": "_Reassigned to @alexandre_", "created_at": "2015-12-10T16:00:16.605Z", "attachment": null}]