[{"author": {"state": "active", "avatar_url": "http://cdn.libravatar.org/avatar/c8b72d0556872a2aea21e8fed0a72001?s=40&d=identicon", "id": 129, "name": "Melissa Wen", "username": "melissawen"}, "id": 10051, "body": "_Milestone changed to [front-end] Melhorias visuais na p\u00e1gina de categorias do painel de admin_", "created_at": "2016-03-04T16:54:03.492Z", "attachment": null}, {"author": {"state": "active", "avatar_url": "http://cdn.libravatar.org/avatar/46c36a7ea48b9a42086ce42e15f40cba?s=40&d=identicon", "id": 83, "name": "Peter Lauro de Lima", "username": "peterlima"}, "id": 9994, "body": "_Status changed to closed_", "created_at": "2016-03-02T16:54:44.065Z", "attachment": null}, {"author": {"state": "active", "avatar_url": "http://cdn.libravatar.org/avatar/c8b72d0556872a2aea21e8fed0a72001?s=40&d=identicon", "id": 129, "name": "Melissa Wen", "username": "melissawen"}, "id": 9478, "body": "para validar em dev", "created_at": "2016-02-18T15:04:14.704Z", "attachment": null}, {"author": {"state": "active", "avatar_url": "http://cdn.libravatar.org/avatar/c8b72d0556872a2aea21e8fed0a72001?s=40&d=identicon", "id": 129, "name": "Melissa Wen", "username": "melissawen"}, "id": 9382, "body": "_Milestone changed to Prioridades - Encerramento_", "created_at": "2016-02-16T13:10:03.489Z", "attachment": null}, {"author": {"state": "active", "avatar_url": "http://cdn.libravatar.org/avatar/c8b72d0556872a2aea21e8fed0a72001?s=40&d=identicon", "id": 129, "name": "Melissa Wen", "username": "melissawen"}, "id": 9380, "body": "_mentioned in commit 2c3dda3c7dd00fe3327c9afcfea9fa126d2ddcd1_", "created_at": "2016-02-16T13:09:55.165Z", "attachment": null}, {"author": {"state": "active", "avatar_url": "http://cdn.libravatar.org/avatar/777e1048d10efb9409d6130aeef27a2f?s=40&d=identicon", "id": 270, "name": "Hebert Santos", "username": "hebertdougl"}, "id": 8975, "body": "_mentioned in merge request !180_", "created_at": "2016-01-27T13:48:54.643Z", "attachment": null}, {"author": {"state": "active", "avatar_url": "http://cdn.libravatar.org/avatar/777e1048d10efb9409d6130aeef27a2f?s=40&d=identicon", "id": 270, "name": "Hebert Santos", "username": "hebertdougl"}, "id": 8921, "body": "@melissawen colocamos bullets nos subn\u00edveis da lista para melhorar esta visualiza\u00e7\u00e3o. Uma alternativa seria criar um estrutura simulando uma \u00e1rvore de diret\u00f3rios, mas por enquanto o @peterlima n\u00e3o acha vi\u00e1vel um refatora\u00e7\u00e3o neste n\u00edvel.", "created_at": "2016-01-26T18:10:12.162Z", "attachment": "categories-list-style-type.png"}, {"author": {"state": "active", "avatar_url": "http://cdn.libravatar.org/avatar/c8b72d0556872a2aea21e8fed0a72001?s=40&d=identicon", "id": 129, "name": "Melissa Wen", "username": "melissawen"}, "id": 8900, "body": "Eu sinto falta de algo para mostrar que a subcategoria est\u00e1 aninhada ao item superior", "created_at": "2016-01-26T17:37:02.519Z", "attachment": null}, {"author": {"state": "active", "avatar_url": "http://cdn.libravatar.org/avatar/777e1048d10efb9409d6130aeef27a2f?s=40&d=identicon", "id": 270, "name": "Hebert Santos", "username": "hebertdougl"}, "id": 8897, "body": "@melissawen Segue a p\u00e1gina de categorias ap\u00f3s a refatora\u00e7\u00e3o realizada em conjunto com o @peterlima.", "created_at": "2016-01-26T17:32:37.019Z", "attachment": "categories.png"}, {"author": {"state": "active", "avatar_url": "http://cdn.libravatar.org/avatar/46c36a7ea48b9a42086ce42e15f40cba?s=40&d=identicon", "id": 83, "name": "Peter Lauro de Lima", "username": "peterlima"}, "id": 8889, "body": "@hebertdougl os \"screenshots\" das modifica\u00e7\u00f5es, devem ser publicados aqui.", "created_at": "2016-01-26T17:10:54.067Z", "attachment": null}]