[{"author": {"state": "active", "avatar_url": "http://cdn.libravatar.org/avatar/4f4b696adc8e8769f43b5c837b3ea23b?s=40&d=identicon", "id": 6, "name": "Marisa Souza dos Santos", "username": "marisa"}, "id": 12986, "body": "homologado no lappis", "created_at": "2016-05-17T19:51:21.177Z", "attachment": null}, {"author": {"state": "active", "avatar_url": "http://cdn.libravatar.org/avatar/b4c7afc2cdffea95a8c2d0387acedc6b?s=40&d=identicon", "id": 15, "name": "Paulo Meireles", "username": "paulormm"}, "id": 11483, "body": "_Status changed to closed_", "created_at": "2016-04-14T22:37:05.081Z", "attachment": null}, {"author": {"state": "active", "avatar_url": "http://cdn.libravatar.org/avatar/b4c7afc2cdffea95a8c2d0387acedc6b?s=40&d=identicon", "id": 15, "name": "Paulo Meireles", "username": "paulormm"}, "id": 11482, "body": "Todas que estiverem fechadas no Milestone de Encerramento ser\u00e3o homologadas pelo MP. Vou fechar para nosso controle interno de encerramento do projeto.\r\n\r\n@kanashiro , @marcosronaldo e @melissawen : para conhecimento.", "created_at": "2016-04-14T22:37:04.946Z", "attachment": null}, {"author": {"state": "active", "avatar_url": "http://cdn.libravatar.org/avatar/b4c7afc2cdffea95a8c2d0387acedc6b?s=40&d=identicon", "id": 15, "name": "Paulo Meireles", "username": "paulormm"}, "id": 11477, "body": "_Reassigned to @lmatos_", "created_at": "2016-04-14T22:29:41.732Z", "attachment": null}, {"author": {"state": "active", "avatar_url": "http://cdn.libravatar.org/avatar/71c7041f7667454f3d6bf8f889e2d598?s=40&d=identicon", "id": 1253, "name": "Luiz Matos", "username": "lmatos"}, "id": 11018, "body": "_Status changed to reopened_", "created_at": "2016-04-11T17:28:22.556Z", "attachment": null}, {"author": {"state": "active", "avatar_url": "http://cdn.libravatar.org/avatar/71c7041f7667454f3d6bf8f889e2d598?s=40&d=identicon", "id": 1253, "name": "Luiz Matos", "username": "lmatos"}, "id": 11017, "body": "Falta Homologar", "created_at": "2016-04-11T17:28:22.502Z", "attachment": null}, {"author": {"state": "active", "avatar_url": "http://cdn.libravatar.org/avatar/8929f5e2c6b39a0a8afb4630b116faab?s=40&d=identicon", "id": 79, "name": "Fabio Teixeira", "username": "fabio1079"}, "id": 10298, "body": "_Status changed to closed_", "created_at": "2016-03-14T17:12:04.082Z", "attachment": null}, {"author": {"state": "active", "avatar_url": "http://cdn.libravatar.org/avatar/79ebee40dd44c661fc4ad27b3656be68?s=40&d=identicon", "id": 252, "name": "\u00c1lvaro Fernando Matos de Souza", "username": "alvarofernandoms"}, "id": 9996, "body": "_mentioned in merge request !214_", "created_at": "2016-03-02T17:12:04.824Z", "attachment": null}, {"author": {"state": "active", "avatar_url": "http://cdn.libravatar.org/avatar/79ebee40dd44c661fc4ad27b3656be68?s=40&d=identicon", "id": 252, "name": "\u00c1lvaro Fernando Matos de Souza", "username": "alvarofernandoms"}, "id": 9979, "body": "_Reassigned to @fabio1079_", "created_at": "2016-03-02T14:34:30.460Z", "attachment": null}, {"author": {"state": "active", "avatar_url": "http://cdn.libravatar.org/avatar/79ebee40dd44c661fc4ad27b3656be68?s=40&d=identicon", "id": 252, "name": "\u00c1lvaro Fernando Matos de Souza", "username": "alvarofernandoms"}, "id": 9978, "body": "_Status changed to reopened_", "created_at": "2016-03-02T14:34:14.340Z", "attachment": null}, {"author": {"state": "active", "avatar_url": "http://cdn.libravatar.org/avatar/79ebee40dd44c661fc4ad27b3656be68?s=40&d=identicon", "id": 252, "name": "\u00c1lvaro Fernando Matos de Souza", "username": "alvarofernandoms"}, "id": 9974, "body": "_Status changed to closed_", "created_at": "2016-03-02T12:56:43.925Z", "attachment": null}, {"author": {"state": "active", "avatar_url": "http://cdn.libravatar.org/avatar/0743c2eb05e68c92baa5f8c498995a20?s=40&d=identicon", "id": 300, "name": "Daniela Feitosa", "username": "daniela"}, "id": 9675, "body": "_mentioned in commit 5bc7a390a0636d5847038d9c4192df2c8587cfae_", "created_at": "2016-02-25T01:05:29.833Z", "attachment": null}, {"author": {"state": "active", "avatar_url": "http://cdn.libravatar.org/avatar/8929f5e2c6b39a0a8afb4630b116faab?s=40&d=identicon", "id": 79, "name": "Fabio Teixeira", "username": "fabio1079"}, "id": 9571, "body": "_mentioned in merge request !191_", "created_at": "2016-02-22T14:21:50.443Z", "attachment": null}, {"author": {"state": "active", "avatar_url": "http://cdn.libravatar.org/avatar/4f4b696adc8e8769f43b5c837b3ea23b?s=40&d=identicon", "id": 6, "name": "Marisa Souza dos Santos", "username": "marisa"}, "id": 9520, "body": "Obrigada @peterlima ", "created_at": "2016-02-19T16:10:39.155Z", "attachment": null}, {"author": {"state": "active", "avatar_url": "http://cdn.libravatar.org/avatar/46c36a7ea48b9a42086ce42e15f40cba?s=40&d=identicon", "id": 83, "name": "Peter Lauro de Lima", "username": "peterlima"}, "id": 9517, "body": "Oi @marisa realizaremos as modifica\u00e7\u00f5es sugeridas. =)", "created_at": "2016-02-19T15:41:03.758Z", "attachment": null}, {"author": {"state": "active", "avatar_url": "http://cdn.libravatar.org/avatar/4f4b696adc8e8769f43b5c837b3ea23b?s=40&d=identicon", "id": 6, "name": "Marisa Souza dos Santos", "username": "marisa"}, "id": 9508, "body": "Oi @peterlima  \u00e9 o texto existente na tooltip. Na verdade o Todos inclui software p\u00fablicos e softwares de governo. Sugest\u00e3o: Softwares p\u00fablicos e softwares que atendem aos requisitos do art. 14 da IN 01/2011, softwares de governo. E em softwares p\u00fablicos tamb\u00e9m alterar para: Software de acordo com os requisitos t\u00e9cnicos e jur\u00eddicos estabelecidos na IN 01/2011.", "created_at": "2016-02-18T19:39:36.972Z", "attachment": null}, {"author": {"state": "active", "avatar_url": "http://cdn.libravatar.org/avatar/46c36a7ea48b9a42086ce42e15f40cba?s=40&d=identicon", "id": 83, "name": "Peter Lauro de Lima", "username": "peterlima"}, "id": 9493, "body": "Oi @marisa @lmatos \r\n\r\nEssa modifica\u00e7\u00e3o, deve ocorrer no r\u00f3tulo \"Todos\", ou no texto complementar, existente na tooltip?\r\n\r\n\r\n\r\n", "created_at": "2016-02-18T18:08:33.078Z", "attachment": "print_catalogo.png"}, {"author": {"state": "active", "avatar_url": "http://cdn.libravatar.org/avatar/79ebee40dd44c661fc4ad27b3656be68?s=40&d=identicon", "id": 252, "name": "\u00c1lvaro Fernando Matos de Souza", "username": "alvarofernandoms"}, "id": 9348, "body": "_Reassigned to @peterlima_", "created_at": "2016-02-15T19:52:52.176Z", "attachment": null}]