[{"author": {"state": "active", "avatar_url": "http://cdn.libravatar.org/avatar/4f4b696adc8e8769f43b5c837b3ea23b?s=40&d=identicon", "id": 6, "name": "Marisa Souza dos Santos", "username": "marisa"}, "id": 8406, "body": "homologada", "created_at": "2016-01-19T13:07:09.652Z", "attachment": null}, {"author": {"state": "active", "avatar_url": "http://cdn.libravatar.org/avatar/4f4b696adc8e8769f43b5c837b3ea23b?s=40&d=identicon", "id": 6, "name": "Marisa Souza dos Santos", "username": "marisa"}, "id": 8405, "body": "_Assignee removed_", "created_at": "2016-01-19T13:07:01.537Z", "attachment": null}, {"author": {"state": "active", "avatar_url": "http://cdn.libravatar.org/avatar/b5782cb554a4b36d12017ee18d1b6e9d?s=40&d=identicon", "id": 104, "name": "Simiao Carvalho", "username": "simiaosimis"}, "id": 3928, "body": "_Status changed to closed_", "created_at": "2015-10-05T20:13:13.760Z", "attachment": null}, {"author": {"state": "active", "avatar_url": "http://cdn.libravatar.org/avatar/b5782cb554a4b36d12017ee18d1b6e9d?s=40&d=identicon", "id": 104, "name": "Simiao Carvalho", "username": "simiaosimis"}, "id": 3927, "body": "Issue fechada com o commit:\r\nhttps://softwarepublico.gov.br/gitlab/softwarepublico/mpog_software/commit/8f80f666d6a0b008deb79d9477fcaeddba96d48a", "created_at": "2015-10-05T20:13:13.551Z", "attachment": null}]