[{"author": {"state": "active", "avatar_url": "http://cdn.libravatar.org/avatar/c8b72d0556872a2aea21e8fed0a72001?s=40&d=identicon", "id": 129, "name": "Melissa Wen", "username": "melissawen"}, "id": 7439, "body": "_Status changed to closed_", "created_at": "2016-01-07T13:22:03.847Z", "attachment": null}, {"author": {"state": "active", "avatar_url": "http://cdn.libravatar.org/avatar/79ebee40dd44c661fc4ad27b3656be68?s=40&d=identicon", "id": 252, "name": "\u00c1lvaro Fernando Matos de Souza", "username": "alvarofernandoms"}, "id": 7379, "body": "_mentioned in commit 0633bb22cbde802d8f8989fe42318ddf01303938_", "created_at": "2016-01-06T19:44:32.741Z", "attachment": null}, {"author": {"state": "active", "avatar_url": "http://cdn.libravatar.org/avatar/c8b72d0556872a2aea21e8fed0a72001?s=40&d=identicon", "id": 129, "name": "Melissa Wen", "username": "melissawen"}, "id": 7377, "body": "_mentioned in commit d678e43bfe9c866f4d7d4e1a72c0444fc6354a8d_", "created_at": "2016-01-06T19:38:10.148Z", "attachment": null}, {"author": {"state": "active", "avatar_url": "http://cdn.libravatar.org/avatar/79ebee40dd44c661fc4ad27b3656be68?s=40&d=identicon", "id": 252, "name": "\u00c1lvaro Fernando Matos de Souza", "username": "alvarofernandoms"}, "id": 7298, "body": "_mentioned in merge request !117_", "created_at": "2016-01-05T20:00:13.836Z", "attachment": null}, {"author": {"state": "active", "avatar_url": "http://cdn.libravatar.org/avatar/79ebee40dd44c661fc4ad27b3656be68?s=40&d=identicon", "id": 252, "name": "\u00c1lvaro Fernando Matos de Souza", "username": "alvarofernandoms"}, "id": 7297, "body": "_mentioned in commit b2b5df5247ccd261da29ab3babb2275141de3685_", "created_at": "2016-01-05T19:55:16.611Z", "attachment": null}, {"author": {"state": "active", "avatar_url": "http://cdn.libravatar.org/avatar/79ebee40dd44c661fc4ad27b3656be68?s=40&d=identicon", "id": 252, "name": "\u00c1lvaro Fernando Matos de Souza", "username": "alvarofernandoms"}, "id": 7293, "body": "_mentioned in commit c985d724a3d970090affaf3ad2ee62939f055bc1_", "created_at": "2016-01-05T19:06:48.097Z", "attachment": null}]